ucenum.py
ucinfo.py
uctools-1.0.2.dist-info/METADATA
uctools-1.0.2.dist-info/RECORD
uctools-1.0.2.dist-info/WHEEL
uctools-1.0.2.dist-info/entry_points.txt
uctools-1.0.2.dist-info/top_level.txt
