Metadata-Version: 2.1
Name: uctools
Version: 1.0.2
Summary: Tools for showing information about unicode characters.
Home-page: https://github.com/luismsgomes/ucinfo
Author: Luís Gomes
Author-email: luismsgomes@gmail.com
License: MIT
Keywords: text unicode character
Platform: UNKNOWN
Classifier: Development Status :: 5 - Production/Stable
Classifier: Intended Audience :: Developers
Classifier: Topic :: Text Processing :: General
Classifier: License :: OSI Approved :: MIT License
Classifier: Programming Language :: Python :: 3
